setup.py
esxi/__init__.py
esxi/argument.py
esxi/esxi.py
esxi/subcommands/__init__.py
esxi/subcommands/deploy.py
esxi/subcommands/destroy.py
esxi/subcommands/getip.py
esxi/subcommands/lib.py
esxi/subcommands/list.py
esxi/subcommands/power.py
pyxenter.egg-info/PKG-INFO
pyxenter.egg-info/SOURCES.txt
pyxenter.egg-info/dependency_links.txt
pyxenter.egg-info/entry_points.txt
pyxenter.egg-info/requires.txt
pyxenter.egg-info/top_level.txt
xen/__init__.py
xen/argument.py
xen/xen.py
xen/subcommands/__init__.py
xen/subcommands/destroy.py
xen/subcommands/getip.py
xen/subcommands/install.py
xen/subcommands/lib.py
xen/subcommands/list.py
xen/subcommands/power.py