Metadata-Version: 1.1
Name: pyxenter
Version: 1.1.0
Summary: ESXi Server and Xen Server control script.
Home-page: https://github.com/corrupt952/Pyxenter
Author: Kazuki Hasegawa
Author-email: hasegawa_0204@hotmail.co.jp
License: BSD
Platform: UNKNOWN
Classifier: Programming Language :: Python
Classifier: Programming Language :: Python :: 2.7
Classifier: Operating System :: OS Independent
Classifier: Development Status :: 2 - Pre-Alpha
Classifier: License :: OSI Approved :: BSD License
